[
    {   
        "id": 1,
        "name": "Hardware industry",
        "img": "https://i.ibb.co/3rHg2LC/travel.png",
        "description": "I have shown simple design in UI. Where we show some products,reviews, sales reports and some of our systems"
    },
    {
        "id": 2,
        "name": "Motocycle repaire",
        "img": "https://i.ibb.co/bgvvgZn/motocycle.png",
        "description":"Here I have highlighted the different services of motorcycles . In this project I have used React Js on client side and firebase used for Authentication"
    },
    {
        "id": 3,
        "name": "WareHouse Telecom Products",
        "img": "https://i.ibb.co/JrrHTbS/keytwo.png",
        "description":"This site has shown products that are stored. Here you can increase the number of products and delete the product if you want. In this project I have used React Js on client side and firebase used for Authentication"
    }
]